picozero/__init__.py
picozero/picozero.py
picozero_rw-0.4.5.dist-info/LICENSE.md
picozero_rw-0.4.5.dist-info/METADATA
picozero_rw-0.4.5.dist-info/WHEEL
picozero_rw-0.4.5.dist-info/top_level.txt
picozero_rw-0.4.5.dist-info/RECORD
