Metadata-Version: 2.1
Name: picozero-rw
Version: 0.4.5
Summary: This is a fork of the origin picozero library
Home-page: https://github.com/roboticsware/picozero
Author: Roboticsware
Author-email: roboticsware_uz@gmail.com
License: MIT
Keywords: raspberry,pi,pico,electronics,roboticsware
Classifier: Development Status :: 4 - Beta
Classifier: Intended Audience :: Developers
Classifier: Intended Audience :: Education
Classifier: Programming Language :: Python :: Implementation :: MicroPython
License-File: LICENSE.md
